FoundationDesign/__init__.py
FoundationDesign/combinedfootingdesign.py
FoundationDesign/concretedesignfunc.py
FoundationDesign/datavalidation.py
FoundationDesign/foundationdesign.py
FoundationDesign-0.1.2.dist-info/LICENSE
FoundationDesign-0.1.2.dist-info/METADATA
FoundationDesign-0.1.2.dist-info/WHEEL
FoundationDesign-0.1.2.dist-info/top_level.txt
FoundationDesign-0.1.2.dist-info/RECORD
