Metadata-Version: 2.1
Name: FoundationDesign
Version: 0.1.2
Summary: A python module for structural analysis and design of different foundation types in accordance to the Eurocodes
Home-page: https://github.com/kunle009/FoundationDesign
Author: Kunle Yusuf
Author-email: kunleyusuf858@gmail.com
Classifier: Programming Language :: Python :: 3.8
Classifier: Programming Language :: Python :: 3.9
Classifier: Programming Language :: Python :: 3.10
Classifier: Programming Language :: Python :: 3.11
Classifier: Programming Language :: Python :: 3.12
Classifier: License :: OSI Approved :: GNU General Public License v3 (GPLv3)
Classifier: Operating System :: OS Independent
Requires-Python: >=3.8
License-File: LICENSE
Requires-Dist: indeterminatebeam ==2.2.1
Requires-Dist: numpy >=1.24.4
Requires-Dist: plotly >=5.15.0
